kurac/__init__.py
kurac/kurac.py
kurac-1.0.2.dist-info/METADATA
kurac-1.0.2.dist-info/WHEEL
kurac-1.0.2.dist-info/top_level.txt
kurac-1.0.2.dist-info/RECORD
