Metadata-Version: 2.1
Name: kurac
Version: 1.0.2
Summary: API Wrapper for Kur.ac.
Home-page: https://github.com/i-vone/kur.ac
Author: i-vone
Author-email: paljetakos@gmail.com
License: UNKNOWN
Keywords: url shortener
Platform: UNKNOWN
Classifier: Development Status :: 5 - Production/Stable
Classifier: Intended Audience :: Developers
Classifier: Programming Language :: Python :: 3
Classifier: Operating System :: Unix
Classifier: Operating System :: MacOS :: MacOS X
Classifier: Operating System :: Microsoft :: Windows
Requires-Dist: requests
